[
  {
    "clientSpecifiedPayloadChecksum": true,
    "createTime": "2024-07-10T22:04:43.790839Z",
    "etag": "\"161cebd56c25f7\"",
    "name": "projects/773781448124/secrets/spaces-digitalocean-s3/versions/2",
    "replicationStatus": {
      "automatic": {}
    },
    "state": "ENABLED"
  },
  {
    "clientSpecifiedPayloadChecksum": true,
    "createTime": "2024-07-10T19:39:00.998105Z",
    "etag": "\"161ce9cc4fb7d9\"",
    "name": "projects/773781448124/secrets/spaces-digitalocean-s3/versions/1",
    "replicationStatus": {
      "automatic": {}
    },
    "state": "ENABLED"
  }
]
